ipyflex/__init__.py
ipyflex/_frontend.py
ipyflex/_version.py
ipyflex/flex_layout.py
ipyflex/utils.py
ipyflex-0.3.1.data/data/share/jupyter/labextensions/ipyflex/package.json
ipyflex-0.3.1.data/data/share/jupyter/labextensions/ipyflex/static/10a19ccb43b25d019582.png
ipyflex-0.3.1.data/data/share/jupyter/labextensions/ipyflex/static/285.43230fbb48fedf1e1552.js
ipyflex-0.3.1.data/data/share/jupyter/labextensions/ipyflex/static/377.038eed744331d14994ef.js
ipyflex-0.3.1.data/data/share/jupyter/labextensions/ipyflex/static/432f3feeb7bc876cf624.png
ipyflex-0.3.1.data/data/share/jupyter/labextensions/ipyflex/static/45.615ed21e5e2d2f976fc2.js
ipyflex-0.3.1.data/data/share/jupyter/labextensions/ipyflex/static/662.b1f67043df0c1c81a4b5.js
ipyflex-0.3.1.data/data/share/jupyter/labextensions/ipyflex/static/666.675e8754c9a2c6733c7f.js
ipyflex-0.3.1.data/data/share/jupyter/labextensions/ipyflex/static/728.c0a338494e11c80aebc6.js
ipyflex-0.3.1.data/data/share/jupyter/labextensions/ipyflex/static/75.ceff401954d3793b41e9.js
ipyflex-0.3.1.data/data/share/jupyter/labextensions/ipyflex/static/75.ceff401954d3793b41e9.js.LICENSE.txt
ipyflex-0.3.1.data/data/share/jupyter/labextensions/ipyflex/static/809.1eb39576bba6769e0608.js
ipyflex-0.3.1.data/data/share/jupyter/labextensions/ipyflex/static/868.fb6ebe7c04fac55108ed.js
ipyflex-0.3.1.data/data/share/jupyter/labextensions/ipyflex/static/939.984d4896b64ba852e80c.js
ipyflex-0.3.1.data/data/share/jupyter/labextensions/ipyflex/static/939.984d4896b64ba852e80c.js.LICENSE.txt
ipyflex-0.3.1.data/data/share/jupyter/labextensions/ipyflex/static/a4d1031cde0d917902be.png
ipyflex-0.3.1.data/data/share/jupyter/labextensions/ipyflex/static/f217706e4e37498c1d29.png
ipyflex-0.3.1.data/data/share/jupyter/labextensions/ipyflex/static/f70ef2dbfb587857b91e.png
ipyflex-0.3.1.data/data/share/jupyter/labextensions/ipyflex/static/remoteEntry.720e049acd56f57dd6e8.js
ipyflex-0.3.1.data/data/share/jupyter/labextensions/ipyflex/static/style.js
ipyflex-0.3.1.dist-info/METADATA
ipyflex-0.3.1.dist-info/WHEEL
ipyflex-0.3.1.dist-info/licenses/LICENSE
ipyflex-0.3.1.dist-info/RECORD
